<?xml version="1.0" encoding="UTF-8"?>
<!-- Created with TexturePacker http://www.codeandweb.com/texturepacker-->
<!-- $TexturePacker:SmartUpdate:5da86d097b9d166be6a3f3eadf54513a:67405ac563bba2e3af158718df751281:b31bb3fd388fd787e9b00954f0b80b18$ -->
<TextureAtlas imagePath="resourceAtlas.png" width="1040" height="1020">
    <SubTexture name="apple_charlotte_icon" x="849" y="818" width="93" height="68" frameX="-4" frameY="-21" frameWidth="100" frameHeight="100"/>
    <SubTexture name="apple_icon" x="283" y="403" width="91" height="95" frameX="-6" frameY="-5" frameWidth="100" frameHeight="100"/>
    <SubTexture name="apple_jam_icon" x="461" y="766" width="78" height="88" frameX="-16" frameY="-9" frameWidth="100" frameHeight="100"/>
    <SubTexture name="apple_juice_icon" x="290" y="2" width="99" height="98" frameX="0" frameY="-2" frameWidth="100" frameHeight="100"/>
    <SubTexture name="bacon_icon" x="780" y="290" width="97" height="91" frameX="0" frameY="-8" frameWidth="100" frameHeight="100"/>
    <SubTexture name="bacon_pie" x="2" y="954" width="98" height="64" frameX="-2" frameY="-22" frameWidth="100" frameHeight="100"/>
    <SubTexture name="bacon_pizza_icon" x="641" y="900" width="96" height="65" frameX="0" frameY="-25" frameWidth="100" frameHeight="100"/>
    <SubTexture name="bacon_with_eggs_icon" x="780" y="199" width="100" height="89" frameX="0" frameY="-7" frameWidth="100" frameHeight="100"/>
    <SubTexture name="baked_potato_icon" x="369" y="756" width="90" height="83" frameX="-5" frameY="-12" frameWidth="100" frameHeight="100"/>
    <SubTexture name="ball_icon" x="588" y="102" width="94" height="98" frameX="-1" frameY="-2" frameWidth="100" frameHeight="100"/>
    <SubTexture name="bear_icon" x="86" y="861" width="69" height="90" frameX="-15" frameY="-5" frameWidth="100" frameHeight="100"/>
    <SubTexture name="berry_juice_icon" x="391" y="2" width="99" height="98" frameX="0" frameY="-2" frameWidth="100" frameHeight="100"/>
    <SubTexture name="berry_pie_icon" x="752" y="571" width="100" height="80" frameX="0" frameY="-14" frameWidth="100" frameHeight="100"/>
    <SubTexture name="berry_yogurt_icon" x="861" y="490" width="96" height="84" frameX="-2" frameY="-8" frameWidth="100" frameHeight="100"/>
    <SubTexture name="blueberry_icon" x="488" y="199" width="93" height="99" frameX="-3" frameY="-1" frameWidth="100" frameHeight="100"/>
    <SubTexture name="blueberry_jam_icon" x="90" y="770" width="70" height="89" frameX="-16" frameY="-8" frameWidth="100" frameHeight="100"/>
    <SubTexture name="blueberry_muffin_icon" x="99" y="478" width="80" height="93" frameX="-8" frameY="-7" frameWidth="100" frameHeight="100"/>
    <SubTexture name="bracelet_icon" x="488" y="102" width="98" height="95" frameX="-1" frameY="-4" frameWidth="100" frameHeight="100"/>
    <SubTexture name="bun_icon" x="361" y="841" width="98" height="74" frameX="0" frameY="-13" frameWidth="100" frameHeight="100"/>
    <SubTexture name="butter_icon" x="846" y="888" width="100" height="59" frameX="0" frameY="-24" frameWidth="100" frameHeight="100"/>
    <SubTexture name="cabbage_icon" x="2" y="570" width="95" height="92" frameX="-3" frameY="-5" frameWidth="100" frameHeight="100"/>
    <SubTexture name="cabbage_pie_icon" x="259" y="760" width="100" height="74" frameX="0" frameY="-12" frameWidth="100" frameHeight="100"/>
    <SubTexture name="cacao_icon" x="961" y="401" width="76" height="85" frameX="-11" frameY="-15" frameWidth="100" frameHeight="100"/>
    <SubTexture name="cap_icon" x="271" y="589" width="100" height="82" frameX="0" frameY="-10" frameWidth="100" frameHeight="100"/>
    <SubTexture name="caramel_apple_icon" x="476" y="491" width="87" height="96" frameX="-10" frameY="-4" frameWidth="100" frameHeight="100"/>
    <SubTexture name="carrot_icon" x="286" y="202" width="92" height="100" frameX="-4" frameY="0" frameWidth="100" frameHeight="100"/>
    <SubTexture name="carrot_juice_icon" x="492" y="2" width="99" height="98" frameX="0" frameY="-2" frameWidth="100" frameHeight="100"/>
    <SubTexture name="carrot_pie_icon" x="251" y="912" width="99" height="74" frameX="-1" frameY="-12" frameWidth="100" frameHeight="100"/>
    <SubTexture name="cheese_icon" x="352" y="917" width="84" height="74" frameX="-8" frameY="-19" frameWidth="100" frameHeight="100"/>
    <SubTexture name="cheeseburger_icon" x="679" y="292" width="99" height="89" frameX="0" frameY="-7" frameWidth="100" frameHeight="100"/>
    <SubTexture name="cherry_icon" x="694" y="2" width="98" height="99" frameX="0" frameY="-1" frameWidth="100" frameHeight="100"/>
    <SubTexture name="cherry_jam_icon" x="2" y="376" width="95" height="95" frameX="-3" frameY="-4" frameWidth="100" frameHeight="100"/>
    <SubTexture name="cherry_juice_icon" x="2" y="664" width="91" height="94" frameX="-6" frameY="-6" frameWidth="100" frameHeight="100"/>
    <SubTexture name="chicken_feed_icon" x="572" y="399" width="99" height="86" frameX="-1" frameY="-12" frameWidth="100" frameHeight="100"/>
    <SubTexture name="chocolate_cake_icon" x="786" y="103" width="95" height="94" frameX="-5" frameY="-6" frameWidth="100" frameHeight="100"/>
    <SubTexture name="chocolate_ice_cream_icon" x="662" y="563" width="88" height="93" frameX="0" frameY="-5" frameWidth="100" frameHeight="100"/>
    <SubTexture name="chocolate_icon" x="747" y="818" width="100" height="67" frameX="0" frameY="-19" frameWidth="100" frameHeight="100"/>
    <SubTexture name="clover_icon" x="868" y="398" width="91" height="90" frameX="-5" frameY="-5" frameWidth="100" frameHeight="100"/>
    <SubTexture name="cookie_icon" x="882" y="203" width="95" height="93" frameX="-3" frameY="-6" frameWidth="100" frameHeight="100"/>
    <SubTexture name="cooper_ore_icon" x="854" y="658" width="89" height="83" frameX="-6" frameY="-9" frameWidth="100" frameHeight="100"/>
    <SubTexture name="copper_bar_icon" x="157" y="939" width="92" height="69" frameX="-4" frameY="-18" frameWidth="100" frameHeight="100"/>
    <SubTexture name="corn_bread_icon" x="739" y="954" width="96" height="64" frameX="-2" frameY="-17" frameWidth="100" frameHeight="100"/>
    <SubTexture name="corn_icon" x="2" y="473" width="95" height="95" frameX="-1" frameY="-3" frameWidth="100" frameHeight="100"/>
    <SubTexture name="corn_syrup_icon" x="2" y="760" width="86" height="98" frameX="-7" frameY="-2" frameWidth="100" frameHeight="100"/>
    <SubTexture name="cotton_candy_icon" x="583" y="298" width="89" height="99" frameX="-4" frameY="0" frameWidth="100" frameHeight="100"/>
    <SubTexture name="cotton_fabric_icon" x="842" y="743" width="100" height="73" frameX="0" frameY="-15" frameWidth="100" frameHeight="100"/>
    <SubTexture name="cotton_icon" x="770" y="477" width="89" height="92" frameX="-6" frameY="-6" frameWidth="100" frameHeight="100"/>
    <SubTexture name="cow_feed_icon" x="376" y="481" width="98" height="87" frameX="-2" frameY="-11" frameWidth="100" frameHeight="100"/>
    <SubTexture name="cream_icon" x="565" y="584" width="95" height="86" frameX="-4" frameY="-12" frameWidth="100" frameHeight="100"/>
    <SubTexture name="croquette_icon" x="464" y="676" width="85" height="88" frameX="-8" frameY="-7" frameWidth="100" frameHeight="100"/>
    <SubTexture name="donut_icon" x="380" y="302" width="100" height="88" frameX="0" frameY="-12" frameWidth="100" frameHeight="100"/>
    <SubTexture name="egg_icon" x="95" y="674" width="72" height="94" frameX="-14" frameY="-5" frameWidth="100" frameHeight="100"/>
    <SubTexture name="french_fries_icon" x="101" y="280" width="82" height="98" frameX="-3" frameY="0" frameWidth="100" frameHeight="100"/>
    <SubTexture name="goat_feed_icon" x="273" y="500" width="98" height="87" frameX="-2" frameY="-11" frameWidth="100" frameHeight="100"/>
    <SubTexture name="goat_milk_icon" x="979" y="203" width="46" height="94" frameX="-27" frameY="-5" frameWidth="100" frameHeight="100"/>
    <SubTexture name="gold_bar_icon" x="945" y="675" width="92" height="69" frameX="-4" frameY="-18" frameWidth="100" frameHeight="100"/>
    <SubTexture name="gold_ore_icon" x="751" y="733" width="89" height="83" frameX="-6" frameY="-9" frameWidth="100" frameHeight="100"/>
    <SubTexture name="grape_ice_cream_icon" x="102" y="179" width="84" height="99" frameX="-13" frameY="-1" frameWidth="100" frameHeight="100"/>
    <SubTexture name="grape_icon" x="2" y="278" width="97" height="96" frameX="-1" frameY="-2" frameWidth="100" frameHeight="100"/>
    <SubTexture name="grape_juice_icon" x="593" y="2" width="99" height="98" frameX="0" frameY="-2" frameWidth="100" frameHeight="100"/>
    <SubTexture name="grape_pie_icon" x="169" y="675" width="100" height="81" frameX="0" frameY="-14" frameWidth="100" frameHeight="100"/>
    <SubTexture name="grape_yogurt_icon" x="466" y="589" width="96" height="85" frameX="-2" frameY="-7" frameWidth="100" frameHeight="100"/>
    <SubTexture name="gratin_icon" x="605" y="967" width="84" height="51" frameX="-8" frameY="-29" frameWidth="100" frameHeight="100"/>
    <SubTexture name="ham_icon" x="774" y="383" width="92" height="92" frameX="-7" frameY="-3" frameWidth="100" frameHeight="100"/>
    <SubTexture name="hamburger_icon" x="377" y="392" width="100" height="87" frameX="0" frameY="-10" frameWidth="100" frameHeight="100"/>
    <SubTexture name="heart_icon" x="684" y="103" width="100" height="90" frameX="0" frameY="-5" frameWidth="100" frameHeight="100"/>
    <SubTexture name="honey_icon" x="390" y="201" width="93" height="99" frameX="-2" frameY="-1" frameWidth="100" frameHeight="100"/>
    <SubTexture name="hotdog_icon" x="438" y="946" width="90" height="67" frameX="-7" frameY="-19" frameWidth="100" frameHeight="100"/>
    <SubTexture name="iron_bar_icon" x="944" y="746" width="92" height="69" frameX="-4" frameY="-18" frameWidth="100" frameHeight="100"/>
    <SubTexture name="iron_ore_icon" x="656" y="746" width="89" height="83" frameX="-6" frameY="-9" frameWidth="100" frameHeight="100"/>
    <SubTexture name="jelly_beans_icon" x="541" y="844" width="98" height="64" frameX="-2" frameY="-20" frameWidth="100" frameHeight="100"/>
    <SubTexture name="lemon_icon" x="479" y="395" width="91" height="94" frameX="-8" frameY="-6" frameWidth="100" frameHeight="100"/>
    <SubTexture name="lemon_pie" x="259" y="836" width="100" height="74" frameX="0" frameY="-12" frameWidth="100" frameHeight="100"/>
    <SubTexture name="meat_icon" x="662" y="658" width="87" height="86" frameX="-7" frameY="-11" frameWidth="100" frameHeight="100"/>
    <SubTexture name="meat_pie_icon" x="752" y="653" width="100" height="78" frameX="0" frameY="-14" frameWidth="100" frameHeight="100"/>
    <SubTexture name="milk_bottle_icon" x="996" y="2" width="42" height="95" frameX="-28" frameY="-1" frameWidth="100" frameHeight="100"/>
    <SubTexture name="necklace_icon" x="2" y="860" width="82" height="92" frameX="-9" frameY="-6" frameWidth="100" frameHeight="100"/>
    <SubTexture name="omelette_icon" x="854" y="576" width="100" height="80" frameX="0" frameY="-8" frameWidth="100" frameHeight="100"/>
    <SubTexture name="orange_icon" x="684" y="195" width="94" height="95" frameX="-3" frameY="-5" frameWidth="100" frameHeight="100"/>
    <SubTexture name="orange_jam_icon" x="99" y="573" width="70" height="99" frameX="-16" frameY="0" frameWidth="100" frameHeight="100"/>
    <SubTexture name="orange_juice_icon" x="2" y="179" width="98" height="97" frameX="0" frameY="-3" frameWidth="100" frameHeight="100"/>
    <SubTexture name="pancake_icon" x="181" y="398" width="100" height="88" frameX="0" frameY="-9" frameWidth="100" frameHeight="100"/>
    <SubTexture name="pants_icon" x="971" y="299" width="63" height="100" frameX="-20" frameY="0" frameWidth="100" frameHeight="100"/>
    <SubTexture name="peper_icon" x="285" y="304" width="90" height="97" frameX="-3" frameY="-3" frameWidth="100" frameHeight="100"/>
    <SubTexture name="pig_feed_icon" x="171" y="586" width="98" height="87" frameX="-2" frameY="-11" frameWidth="100" frameHeight="100"/>
    <SubTexture name="pizza_icon" x="837" y="954" width="96" height="62" frameX="0" frameY="-25" frameWidth="100" frameHeight="100"/>
    <SubTexture name="potato_icon" x="390" y="102" width="96" height="97" frameX="-2" frameY="-3" frameWidth="100" frameHeight="100"/>
    <SubTexture name="powdered_sugar_icon" x="461" y="856" width="70" height="88" frameX="-13" frameY="-11" frameWidth="100" frameHeight="100"/>
    <SubTexture name="product_particle" x="2" y="2" width="184" height="175" frameX="-10" frameY="-25" frameWidth="200" frameHeight="200"/>
    <SubTexture name="pyramid_icon" x="188" y="103" width="96" height="100" frameX="-2" frameY="0" frameWidth="100" frameHeight="100"/>
    <SubTexture name="raisin_bun_icon" x="744" y="887" width="100" height="65" frameX="0" frameY="-21" frameWidth="100" frameHeight="100"/>
    <SubTexture name="raspberry_icon" x="373" y="663" width="89" height="91" frameX="-6" frameY="-7" frameWidth="100" frameHeight="100"/>
    <SubTexture name="raspberry_jam_icon" x="961" y="488" width="70" height="91" frameX="-16" frameY="-6" frameWidth="100" frameHeight="100"/>
    <SubTexture name="raspberry_muffin_icon" x="99" y="380" width="80" height="96" frameX="-8" frameY="-4" frameWidth="100" frameHeight="100"/>
    <SubTexture name="ring_icon" x="162" y="852" width="87" height="85" frameX="-7" frameY="-10" frameWidth="100" frameHeight="100"/>
    <SubTexture name="rose_icon" x="188" y="2" width="100" height="99" frameX="0" frameY="0" frameWidth="100" frameHeight="100"/>
    <SubTexture name="sausage_icon" x="583" y="202" width="94" height="94" frameX="-5" frameY="0" frameWidth="100" frameHeight="100"/>
    <SubTexture name="scarf_icon" x="894" y="101" width="97" height="100" frameX="-2" frameY="0" frameWidth="100" frameHeight="100"/>
    <SubTexture name="sheep_feed_icon" x="674" y="383" width="98" height="87" frameX="-2" frameY="-11" frameWidth="100" frameHeight="100"/>
    <SubTexture name="silver_bar_icon" x="944" y="817" width="92" height="69" frameX="-4" frameY="-18" frameWidth="100" frameHeight="100"/>
    <SubTexture name="silver_ore_icon" x="551" y="759" width="89" height="83" frameX="-6" frameY="-9" frameWidth="100" frameHeight="100"/>
    <SubTexture name="socks_icon" x="185" y="303" width="98" height="93" frameX="0" frameY="-7" frameWidth="100" frameHeight="100"/>
    <SubTexture name="soybean_icon" x="373" y="570" width="91" height="91" frameX="-3" frameY="-7" frameWidth="100" frameHeight="100"/>
    <SubTexture name="spicy_pizza_icon" x="642" y="831" width="100" height="67" frameX="0" frameY="-21" frameWidth="100" frameHeight="100"/>
    <SubTexture name="strawberry_ice_cream_icon" x="169" y="758" width="88" height="92" frameX="0" frameY="-6" frameWidth="100" frameHeight="100"/>
    <SubTexture name="strawberry_icon" x="794" y="2" width="98" height="99" frameX="-2" frameY="0" frameWidth="100" frameHeight="100"/>
    <SubTexture name="strawberry_jam_icon" x="956" y="581" width="82" height="92" frameX="-9" frameY="-6" frameWidth="100" frameHeight="100"/>
    <SubTexture name="strawberry_yogurt_icon" x="271" y="673" width="96" height="85" frameX="-2" frameY="-7" frameWidth="100" frameHeight="100"/>
    <SubTexture name="sugar_icon" x="533" y="910" width="70" height="88" frameX="-13" frameY="-11" frameWidth="100" frameHeight="100"/>
    <SubTexture name="sugarcane_icon" x="572" y="487" width="88" height="95" frameX="-7" frameY="-1" frameWidth="100" frameHeight="100"/>
    <SubTexture name="sweater_icon" x="894" y="2" width="100" height="97" frameX="0" frameY="-3" frameWidth="100" frameHeight="100"/>
    <SubTexture name="toffee_icon" x="673" y="472" width="95" height="89" frameX="-3" frameY="-8" frameWidth="100" frameHeight="100"/>
    <SubTexture name="tomato_icon" x="188" y="205" width="95" height="96" frameX="-2" frameY="-2" frameWidth="100" frameHeight="100"/>
    <SubTexture name="tomato_juice_icon" x="290" y="102" width="98" height="98" frameX="0" frameY="-2" frameWidth="100" frameHeight="100"/>
    <SubTexture name="vanllla_ice_cream_icon" x="564" y="672" width="90" height="85" frameX="-7" frameY="-15" frameWidth="100" frameHeight="100"/>
    <SubTexture name="wheat_icon" x="879" y="298" width="90" height="98" frameX="-5" frameY="0" frameWidth="100" frameHeight="100"/>
    <SubTexture name="winter_hat_icon" x="181" y="488" width="90" height="96"/>
    <SubTexture name="wool_icon" x="485" y="300" width="94" height="93" frameX="-2" frameY="-4" frameWidth="100" frameHeight="100"/>
</TextureAtlas>
