{"SubTexture":[{"name":"pier","height":124,"x":0,"y":0,"width":233},{"name":"legRight","height":15,"x":235,"y":100,"width":11},{"name":"tail","height":10,"x":235,"y":69,"width":17},{"name":"handRight","height":17,"x":235,"y":117,"width":9},{"name":"body","height":25,"x":235,"y":0,"width":17},{"name":"kupka","height":9,"x":159,"y":126,"width":12},{"name":"vudka","height":4,"x":37,"y":126,"width":51},{"name":"legLeft","height":15,"x":147,"y":126,"width":10},{"name":"handLeft","height":17,"x":235,"y":81,"width":10},{"name":"head","height":46,"x":0,"y":126,"width":35},{"name":"lips","height":5,"x":247,"y":81,"width":6},{"name":"eyes","height":5,"x":173,"y":126,"width":15},{"name":"truli","height":20,"x":235,"y":27,"width":14},{"name":"poviki","height":22,"x":124,"y":126,"width":21},{"name":"poplavok","height":18,"x":235,"y":49,"width":15},{"name":"viyi","height":11,"x":90,"y":126,"width":32}],"name":"pier","imagePath":"texture.png"}