{"name":"plant","imagePath":"texture.png","SubTexture":[{"name":"Green_1.png","x":369,"height":17,"y":135,"width":20},{"name":"Green_4.png","x":61,"height":17,"y":232,"width":42},{"name":"cabbage_stage_1.png","x":262,"height":21,"y":216,"width":39},{"name":"cabbage_stage_2.png","x":107,"height":35,"y":188,"width":39},{"name":"cabbage_stage_3.png","x":281,"height":39,"y":91,"width":48},{"name":"cabagem","x":288,"height":44,"y":0,"width":54},{"name":"carrot_stage_1.png","x":369,"height":21,"y":91,"width":20},{"name":"Green_1_1.png","x":306,"height":14,"y":189,"width":23},{"name":"Green_1_2.png","x":107,"height":17,"y":225,"width":39},{"name":"Green_1_3.png","x":44,"height":17,"y":251,"width":39},{"name":"Green_1_4.png","x":353,"height":17,"y":235,"width":28},{"name":"carrot_stage_2.png","x":331,"height":33,"y":177,"width":29},{"name":"carrot_stage_3.png","x":479,"height":38,"y":135,"width":29},{"name":"carrotm","x":124,"height":49,"y":48,"width":29},{"name":"Pink_lignt_1.png","x":367,"height":17,"y":173,"width":19},{"name":"Pink_lignt_2.png","x":35,"height":17,"y":148,"width":24},{"name":"clover_stage_1.png","x":29,"height":22,"y":209,"width":30},{"name":"clover_stage_2.png","x":29,"height":22,"y":185,"width":30},{"name":"clover_stage_3.png","x":437,"height":39,"y":89,"width":49},{"name":"cloverm","x":344,"height":44,"y":0,"width":54},{"name":"Pink_1.png","x":35,"height":16,"y":167,"width":23},{"name":"corn_stage_1.png","x":202,"height":36,"y":91,"width":24},{"name":"corn_stage_2.png","x":0,"height":52,"y":126,"width":33},{"name":"corn_stage_3.png","x":118,"height":52,"y":99,"width":33},{"name":"cornm","x":391,"height":52,"y":101,"width":33},{"name":"cotone_stage_1.png","x":369,"height":19,"y":114,"width":19},{"name":"Green_light_2_2.png","x":200,"height":15,"y":164,"width":24},{"name":"cotone_stage_2.png","x":0,"height":28,"y":180,"width":27},{"name":"cotone_stage_3.png","x":116,"height":33,"y":153,"width":32},{"name":"cotonem","x":391,"height":33,"y":155,"width":32},{"name":"Red_1.png","x":367,"height":17,"y":154,"width":22},{"name":"Red_2.png","x":488,"height":17,"y":116,"width":22},{"name":"Red_3.png","x":201,"height":17,"y":238,"width":42},{"name":"Red_4.png","x":245,"height":17,"y":239,"width":42},{"name":"grape_stages_1.png","x":331,"height":32,"y":143,"width":34},{"name":"grape_stages_2.png","x":70,"height":39,"y":48,"width":52},{"name":"grape_stages_3.png","x":153,"height":38,"y":100,"width":47},{"name":"grapem","x":446,"height":42,"y":0,"width":52},{"name":"heart_stage_1.png","x":425,"height":41,"y":164,"width":40},{"name":"heart_stage_2.png","x":231,"height":50,"y":0,"width":55},{"name":"heart_stage_3.png","x":158,"height":50,"y":0,"width":71},{"name":"__dbTextures/heart/Layer 2_3","x":420,"height":16,"y":236,"width":41},{"name":"heart_o","x":340,"height":43,"y":46,"width":49},{"name":"Yellow_light_1.png","x":383,"height":16,"y":251,"width":28},{"name":"Yellow_light_3.png","x":289,"height":17,"y":239,"width":39},{"name":"papper_stage_1.png","x":150,"height":31,"y":179,"width":45},{"name":"papper_stage_2.png","x":148,"height":27,"y":212,"width":51},{"name":"papper_stage_3.png","x":63,"height":32,"y":126,"width":51},{"name":"papperm","x":228,"height":39,"y":52,"width":51},{"name":"potato_stage_1.png","x":463,"height":22,"y":214,"width":42},{"name":"Red_light_3.png","x":202,"height":17,"y":129,"width":24},{"name":"Red_light_4.png","x":0,"height":17,"y":233,"width":42},{"name":"potato_stage_2.png","x":306,"height":25,"y":212,"width":45},{"name":"potato_stage_3.png","x":221,"height":31,"y":205,"width":39},{"name":"potatom","x":63,"height":35,"y":89,"width":53},{"name":"Symbol 1","x":70,"height":46,"y":0,"width":86},{"name":"pink_rose_stage_1.png copy","x":288,"height":43,"y":46,"width":50},{"name":"pink_rose_stage_1.png","x":446,"height":43,"y":44,"width":50},{"name":"rose_an","x":0,"height":68,"y":0,"width":68},{"name":"Green_light_1_1.png","x":0,"height":15,"y":252,"width":28},{"name":"Green_light_1_2.png","x":388,"height":17,"y":213,"width":33},{"name":"Green_light_1_3.png","x":148,"height":17,"y":241,"width":39},{"name":"soybean_stage_1.png","x":423,"height":27,"y":207,"width":38},{"name":"soybean_stage_2.png","x":153,"height":37,"y":140,"width":45},{"name":"soybean_stage_3.png","x":0,"height":25,"y":99,"width":61},{"name":"soebinm","x":0,"height":27,"y":70,"width":61},{"name":"Green_dark_1.png","x":312,"height":12,"y":132,"width":17},{"name":"Green_dark_2.png","x":388,"height":17,"y":232,"width":30},{"name":"Green_dark_3.png","x":105,"height":17,"y":244,"width":39},{"name":"strawberry_stage_1.png","x":35,"height":20,"y":126,"width":26},{"name":"strawberry_stage_2.png","x":426,"height":32,"y":130,"width":51},{"name":"strawberry_stage_3.png","x":467,"height":37,"y":175,"width":39},{"name":"strawb","x":264,"height":41,"y":173,"width":40},{"name":"sugarcane_stage_1.png","x":61,"height":30,"y":200,"width":44},{"name":"Yellow_1.png","x":388,"height":21,"y":190,"width":33},{"name":"Yellow_2.png","x":353,"height":21,"y":212,"width":33},{"name":"sugarcane_stage_2.png","x":61,"height":38,"y":160,"width":44},{"name":"sugarcane_stage_3.png","x":391,"height":46,"y":53,"width":44},{"name":"sugar","x":400,"height":51,"y":0,"width":44},{"name":"tomato_stage_1.png","x":226,"height":25,"y":178,"width":34},{"name":"Blue_dark_3.png","x":200,"height":14,"y":148,"width":25},{"name":"Blue_dark_4.png","x":463,"height":17,"y":238,"width":42},{"name":"tomato_stage_2.png","x":228,"height":31,"y":145,"width":34},{"name":"tomato_stage_3.png","x":266,"height":39,"y":132,"width":44},{"name":"tomatom","x":155,"height":46,"y":52,"width":45},{"name":"Blue_1.png","x":197,"height":13,"y":196,"width":22},{"name":"Blue_2.png","x":362,"height":13,"y":192,"width":22},{"name":"Blue_3.png","x":197,"height":13,"y":181,"width":24},{"name":"Blue_4 (1).png","x":306,"height":14,"y":173,"width":23},{"name":"wheat_stage_1 (1).png","x":488,"height":25,"y":89,"width":20},{"name":"wheat_stage_2 (1).png","x":202,"height":37,"y":52,"width":24},{"name":"wheat_stage_3 (1).png","x":228,"height":50,"y":93,"width":36},{"name":"wheatm","x":331,"height":50,"y":91,"width":36}]}